{
  "list": [
    "ASA: The Island",
    "The Island",
    "Scorched Earth",
    "Aberration",
    "Extinction",
    "Genesis: Part 1",
    "Genesis: Part 2",
    "-",
    "The Center",
    "Ragnarok",
    "Valguero",
    "Crystal Isles",
    "Lost Island",
    "Fjordur"
  ],
  "maps": [
    {
      "name": "ASA: The Island",
      "folder": "The_Island_ASA",
      "maps": [
        {
          "resource": "The_Island_Ressources.json",
          "exploration": "The_Island_Exploration.json",
          "map_coord": {
            "offset": {
              "lat": 50,
              "lon": 50
            },
            "mult": {
              "lat": 8000,
              "lon": 8000
            }
          }
        }
      ]
    },
    {
      "name": "The Island",
      "folder": "The_Island",
      "maps": [
        {
          "resource": "The_Island_Ressources.json",
          "exploration": "The_Island_Exploration.json",
          "map_border": {
            "width": 30,
            "color": "#246be1"
          }
        }
      ]
    },
    {
      "name": "The Center",
      "folder": "The_Center",
      "maps": [
        {
          "resource": "The_Center_Ressources.json",
          "exploration": "The_Center_Exploration.json"
        }
      ]
    },
    {
      "name": "Scorched Earth",
      "folder": "Scorched_Earth",
      "maps": [
        {
          "resource": "Scorched_Earth_Ressources.json",
          "exploration": "Scorched_Earth_Exploration.json"
        }
      ]
    },
    {
      "name": "Ragnarok",
      "folder": "Ragnarok",
      "maps": [
        {
          "resource": "Ragnarok_Ressources.json",
          "exploration": "Ragnarok_Exploration.json"
        }
      ]
    },
    {
      "name": "Aberration",
      "folder": "Aberration",
      "maps": [
        {
          "resource": "Aberration_Ressources.json",
          "exploration": "Aberration_Exploration.json",
          "map_border": {
            "width": 30,
            "color": "#808080"
          }
        }
      ]
    },
    {
      "name": "Extinction",
      "folder": "Extinction",
      "maps": [
        {
          "resource": "Extinction_Ressources.json",
          "exploration": "Extinction_Exploration.json",
          "map_border": {
            "width": 200,
            "color": "#776e65"
          }
        }
      ]
    },
    {
      "name": "Valguero",
      "folder": "Valguero",
      "maps": [
        {
          "resource": "Valguero_Ressources.json",
          "exploration": "Valguero_Exploration.json"
        }
      ]
    },
    {
      "name": "Genesis: Part 1",
      "folder": "Genesis_Part_1",
      "maps": [
        {
          "resource": "Genesis_Part_1_Ressources.json",
          "exploration": "Genesis_Part_1_Exploration.json",
          "map_border": {
            "width": 50,
            "color": "#909090"
          }
        }
      ]
    },
    {
      "name": "Genesis: Part 2",
      "folder": "Genesis_Part_2",
      "maps": [
        {
          "resource": "Genesis_Part_2_Ressources.json",
          "exploration": "Genesis_Part_2_Exploration.json"
        }
      ]
    },
    {
      "name": "Crystal Isles",
      "folder": "Crystal_Isles",
      "maps": [
        {
          "resource": "Crystal_Isles_Ressources.json",
          "exploration": "Crystal_Isles_Exploration.json",
          "map_border": {
            "width": 100,
            "color": "#0c7edf"
          }
        }
      ]
    },
    {
      "name": "Lost Island",
      "folder": "Lost_Island",
      "maps": [
        {
          "resource": "Lost_Island_Ressources.json",
          "exploration": "Lost_Island_Exploration.json"
        }
      ]
    },
    {
      "name": "Fjordur",
      "folder": "Fjordur",
      "maps": [
        {
          "name": "Midgard",
          "resource": "Fjordur_Midgard_Ressources.json",
          "exploration": "Fjordur_Midgard_Exploration.json",
          "map_border": {
            "width": 100,
            "color": "#2955dc"
          }
        },
        {
          "name": "Asgard",
          "resource": "Fjordur_Asgard_Ressources.json",
          "exploration": "Fjordur_Asgard_Exploration.json"
        },
        {
          "name": "Jotunheim",
          "resource": "Fjordur_Jotunheim_Ressources.json",
          "exploration": "Fjordur_Jotunheim_Exploration.json"
        },
        {
          "name": "Vanaheim",
          "resource": "Fjordur_Vanaheim_Ressources.json",
          "exploration": "Fjordur_Vanaheim_Exploration.json"
        }
      ]
    }
  ]
}
